HighDim/Test_density.py
HighDim/__init__.py
HighDim/density.py
HighDim-0.0.3.dist-info/METADATA
HighDim-0.0.3.dist-info/WHEEL
HighDim-0.0.3.dist-info/top_level.txt
HighDim-0.0.3.dist-info/RECORD
