Metadata-Version: 2.1
Name: HighDim
Version: 0.0.3
Summary: HighDim is a numerical package for computing the marginal density distribution.
Home-page: https://github.com/liyo6397/high_dimensional_density
Author: Lily Young
Author-email: lilyyoung1122@gmail.com
License: UNKNOWN
Keywords: python,high dimensional data
Platform: UNKNOWN
Classifier: Intended Audience :: Science/Research
Classifier: Programming Language :: Python :: 3
Classifier: Operating System :: MacOS :: MacOS X
Classifier: Operating System :: Microsoft :: Windows
Requires-Dist: numpy
Requires-Dist: scipy
